lbt_recipes/__init__.py
lbt_recipes/__main__.py
lbt_recipes/recipe.py
lbt_recipes/settings.py
lbt_recipes/version.py
lbt_recipes/adaptive_comfort_map/package.json
lbt_recipes/adaptive_comfort_map/run.py
lbt_recipes/adaptive_comfort_map/status.json
lbt_recipes/adaptive_comfort_map/flow/__init__.py
lbt_recipes/adaptive_comfort_map/flow/main_6b5ce744.py
lbt_recipes/adaptive_comfort_map/flow/dependencies/__init__.py
lbt_recipes/adaptive_comfort_map/flow/dependencies/comfort_mapping_entry_point.py
lbt_recipes/adaptive_comfort_map/flow/dependencies/dynamic_contribution_entry_point.py
lbt_recipes/adaptive_comfort_map/flow/dependencies/dynamic_shade_contrib_entry_point.py
lbt_recipes/adaptive_comfort_map/flow/dependencies/energy_simulation.py
lbt_recipes/adaptive_comfort_map/flow/dependencies/prepare_folder.py
lbt_recipes/adaptive_comfort_map/flow/dependencies/radiance_mapping_entry_point.py
lbt_recipes/adaptive_comfort_map/flow/dependencies/spherical_view_factor_entry_point.py
lbt_recipes/adaptive_comfort_map/flow/dependencies/dependencies/__init__.py
lbt_recipes/adaptive_comfort_map/flow/dependencies/dependencies/radiance_contrib_entry_point.py
lbt_recipes/adaptive_comfort_map/flow/dependencies/dependencies/shade_contrib_entry_point.py
lbt_recipes/adaptive_comfort_map/flow/dependencies/dependencies/spherical_view_factor.py
lbt_recipes/annual_daylight/package.json
lbt_recipes/annual_daylight/run.py
lbt_recipes/annual_daylight/status.json
lbt_recipes/annual_daylight/flow/__init__.py
lbt_recipes/annual_daylight/flow/main_28ff6c38.py
lbt_recipes/annual_daylight/flow/main_e6056798.py
lbt_recipes/annual_daylight/flow/dependencies/__init__.py
lbt_recipes/annual_daylight/flow/dependencies/annual_daylight_post_process.py
lbt_recipes/annual_daylight/flow/dependencies/annual_daylight_prepare_folder.py
lbt_recipes/annual_daylight/flow/dependencies/annual_daylight_ray_tracing.py
lbt_recipes/annual_daylight_enhanced/package.json
lbt_recipes/annual_daylight_enhanced/run.py
lbt_recipes-0.26.25.dist-info/licenses/LICENSE
lbt_recipes-0.26.25.dist-info/METADATA
lbt_recipes-0.26.25.dist-info/WHEEL
lbt_recipes-0.26.25.dist-info/entry_points.txt
lbt_recipes-0.26.25.dist-info/top_level.txt
lbt_recipes-0.26.25.dist-info/RECORD
