Metadata-Version: 2.4
Name: lbt-recipes
Version: 0.26.25
Summary: A collection of recipes that ship with the Ladybug Tools plugins.
Home-page: https://github.com/ladybug-tools/lbt-recipes
Author: Ladybug Tools
Author-email: info@ladybug.tools
License: AGPL-3.0
Classifier: Programming Language :: Python :: 3.7
Classifier: Programming Language :: Python :: 3.8
Classifier: Programming Language :: Python :: 3.9
Classifier: Programming Language :: Python :: 3.10
Classifier: Programming Language :: Python :: 3.11
Classifier: Programming Language :: Python :: 3.12
Classifier: Programming Language :: Python :: Implementation :: CPython
Classifier: Operating System :: OS Independent
License-File: LICENSE
Requires-Dist: queenbee-local==0.7.0; python_version >= "3.8"
Requires-Dist: queenbee-local==0.6.2; python_version < "3.8"
Requires-Dist: pollination-handlers==0.10.12
Requires-Dist: click==7.1.2; python_version < "3.8"
Requires-Dist: click==8.1.7; python_version >= "3.8"
Dynamic: author
Dynamic: author-email
Dynamic: classifier
Dynamic: description
Dynamic: description-content-type
Dynamic: home-page
Dynamic: license
Dynamic: license-file
Dynamic: requires-dist
Dynamic: summary
